{
  "source_file": "data/325-10-5M-46dB-1.csv",
  "start_point_us": 17.55,
  "num_positions": 2,
  "speed_of_sound": 1540,
  "positions": [
    {
      "position_number": 1,
      "position_name": "Dermis",
      "time_us": 20.169999999999998,
      "thickness_mm": 2.017399999999999,
      "depth_start_mm": 0.0,
      "depth_end_mm": 2.017399999999999
    },
    {
      "position_number": 2,
      "position_name": "Fascia",
      "time_us": 22.779999999999998,
      "thickness_mm": 4.0271,
      "depth_start_mm": 2.017399999999999,
      "depth_end_mm": 4.0271
    }
  ]
}