{
  "source_file": "data/hjbaek-5M-7.csv",
  "start_point_us": 17.38,
  "num_positions": 2,
  "speed_of_sound": 1540,
  "positions": [
    {
      "position_number": 1,
      "position_name": "Dermis",
      "time_us": 19.43,
      "thickness_mm": 1.5784999999999991,
      "depth_start_mm": 0.0,
      "depth_end_mm": 1.5784999999999991
    },
    {
      "position_number": 2,
      "position_name": "Fascia",
      "time_us": 21.71,
      "thickness_mm": 3.3341000000000007,
      "depth_start_mm": 1.5784999999999991,
      "depth_end_mm": 3.3341000000000007
    }
  ]
}